{"crushers":[{"first_name":"Alexandra","last_name":"Lee","twitter_username":"alexandrawlee","website":"http://twitter.com/alexandrawlee","photo":{"url":"http://twitter.com/alexandrawlee"},"job":{"position":"Directory of Business Development","company":{"name":"Crush + Lovely","website":"http://crushlovely.com"}}},{"first_name":"Michael","last_name":"Phillips","twitter_username":"createbang","website":"http://createbang.com","photo":{"url":"myimage.jpg"},"job":{"position":"Developer","company":{"name":"Crush + Lovely","website":"http://crushlovely.com"}}}]}